bc_configs/__init__.py
bc_configs/py.typed
bc_configs/configurator/BaseConfig.py
bc_configs/configurator/__init__.py
bc_configs/environ_source/EnvironSourceException.py
bc_configs/environ_source/VaultConfig.py
bc_configs/environ_source/__init__.py
bc_configs/environ_source/define.py
bc_configs-0.2.2.dist-info/METADATA
bc_configs-0.2.2.dist-info/WHEEL
bc_configs-0.2.2.dist-info/licenses/LICENSE
bc_configs-0.2.2.dist-info/RECORD
