Metadata-Version: 2.4
Name: bc-configs
Version: 0.2.2
Summary: Configuration module, that provides a way to manage configs structure, validation and casting to type inside your code. Based on pedantic models. Additionally it can automatically getting config from environment variables, .env, HashiCorp Vault, etc.
Project-URL: Homepage, https://github.com/etagi-esoft/py-bc-configs
Project-URL: Repository, https://github.com/etagi-esoft/py-bc-configs
Author-email: Artem Shirokikh <job@artemetr.ru>, Esoft <it@esoft.tech>
License: MIT
License-File: LICENSE
Keywords: config,dotenv,environment,pydantic
Classifier: Development Status :: 5 - Production/Stable
Classifier: Environment :: Console
Classifier: Environment :: MacOS X
Classifier: Intended Audience :: Developers
Classifier: Intended Audience :: Information Technology
Classifier: Intended Audience :: System Administrators
Classifier: Operating System :: POSIX :: Linux
Classifier: Operating System :: Unix
Classifier: Programming Language :: Python
Classifier: Programming Language :: Python :: 3
Classifier: Programming Language :: Python :: 3.13
Classifier: Programming Language :: Python :: Implementation :: CPython
Classifier: Programming Language :: Python :: Implementation :: PyPy
Classifier: Topic :: Internet
Classifier: Topic :: Software Development :: Libraries :: Python Modules
Requires-Python: >=3.13
Requires-Dist: pydantic
